MANIFEST.in
requirements.txt
setup.py
glitch/__init__.py
glitch/glitch.py
glitch.egg-info/PKG-INFO
glitch.egg-info/SOURCES.txt
glitch.egg-info/dependency_links.txt
glitch.egg-info/entry_points.txt
glitch.egg-info/requires.txt
glitch.egg-info/top_level.txt