Metadata-Version: 1.1
Name: glitch
Version: 1.1.2
Summary: glitch jpg files
Home-page: https://github.com/trsqxyz/glitch
Author: trsqxyz
Author-email: trsqxyz@gmail.com
License: MIT
Platform: UNKNOWN
Classifier: Programming Language :: Python :: 3.4
Classifier: License :: OSI Approved :: MIT License
